djbookshelf/__init__.py
djbookshelf/admin.py
djbookshelf/apps.py
djbookshelf/exceptions.py
djbookshelf/migrations/0001_initial.py
djbookshelf/migrations/0002_auto_20211228_2239.py
djbookshelf/migrations/__init__.py
djbookshelf/models/__init__.py
djbookshelf/models/author.py
djbookshelf/models/book.py
djbookshelf/models/isbn.py
djbookshelf/models/language.py
djbookshelf/models/publisher.py
djbookshelf/templates/djbookshelf/core.html
djbookshelf/urls.py
djbookshelf/utility.py
djbookshelf/views.py
djbookshelf-0.1.4.dist-info/LICENSE
djbookshelf-0.1.4.dist-info/WHEEL
djbookshelf-0.1.4.dist-info/METADATA
djbookshelf-0.1.4.dist-info/RECORD
